README.rst
setup.cfg
setup.py
snarky/__init__.py
snarky/decorators.py
snarky/version.py
snarky.egg-info/PKG-INFO
snarky.egg-info/SOURCES.txt
snarky.egg-info/dependency_links.txt
snarky.egg-info/requires.txt
snarky.egg-info/top_level.txt