Metadata-Version: 1.1
Name: snarky
Version: 0.0.1
Summary: Snarky adds a 'jk' (just kidding!) keyword argument to any function.
Home-page: https://github.com/eackermann/snarky/
Author: Etienne Ackermann
Author-email: era3@rice.edu
License: MIT License
Download-URL: https://github.com/eackermann/snarky/tarball/0.0.1
Keywords: useless kidding
Platform: any
